multplic/__init__.py
multplic/multiplicando.py
multplicaparalelogramo/__init__.py
multplicaparalelogramo/multiplicando.py
multiplicparalelogramo-0.0.3.dist-info/LICENSE
multiplicparalelogramo-0.0.3.dist-info/METADATA
multiplicparalelogramo-0.0.3.dist-info/WHEEL
multiplicparalelogramo-0.0.3.dist-info/top_level.txt
multiplicparalelogramo-0.0.3.dist-info/RECORD
