Metadata-Version: 2.1
Name: multiplicparalelogramo
Version: 0.0.3
Summary: Meu primeiro pacote em python
Author: Luis Eduardo
Author-email: le1307114@gmail.com
Keywords: python pacote example
License-File: LICENSE
